aws_arn_delete/__init__.py
aws_arn_delete-0.1.2.dist-info/LICENSE
aws_arn_delete-0.1.2.dist-info/WHEEL
aws_arn_delete-0.1.2.dist-info/METADATA
aws_arn_delete-0.1.2.dist-info/RECORD
