Metadata-Version: 2.1
Name: aws-arn-delete
Version: 0.1.2
Summary: Delete AWS resources based off its ARN
Home-page: https://github.com/cfarrend/aws-arn-delete
License: MIT
Keywords: aws,batect,pip,poetry,python3
Author: Christopher Farrenden
Author-email: cfarrend@gmail.com
Requires-Python: >=3.7.4,<4.0.0
Classifier: License :: OSI Approved :: MIT License
Classifier: Programming Language :: Python :: 3
Requires-Dist: toml (>=0.9,<0.10)
Project-URL: Repository, https://github.com/cfarrend/aws-arn-delete
